diffusionx-0.2.1.dist-info/METADATA
diffusionx-0.2.1.dist-info/WHEEL
diffusionx-0.2.1.dist-info/licenses/LICENSE-APACHE
diffusionx-0.2.1.dist-info/licenses/LICENSE-MIT
diffusionx/__init__.py
diffusionx/_core.abi3.so
diffusionx/_core.pyi
diffusionx/distribution.py
diffusionx/py.typed
diffusionx/random.py
diffusionx/simulation/__init__.py
diffusionx/simulation/basic.py
diffusionx/simulation/bb.py
diffusionx/simulation/be.py
diffusionx/simulation/bm.py
diffusionx/simulation/cauchy.py
diffusionx/simulation/ctrw.py
diffusionx/simulation/fbm.py
diffusionx/simulation/gamma.py
diffusionx/simulation/gb.py
diffusionx/simulation/langevin.py
diffusionx/simulation/levy.py
diffusionx/simulation/levy_walk.py
diffusionx/simulation/meander.py
diffusionx/simulation/ou.py
diffusionx/simulation/poisson.py
diffusionx/simulation/utils.py
diffusionx/types.py
diffusionx-0.2.1.dist-info/RECORD
