Metadata-Version: 2.4
Name: diffusionx
Version: 0.2.1
Classifier: Development Status :: 4 - Beta
Classifier: Intended Audience :: Science/Research
Classifier: License :: OSI Approved :: MIT License
Classifier: Operating System :: OS Independent
Classifier: Programming Language :: Python :: 3
Classifier: Programming Language :: Python :: 3.11
Classifier: Programming Language :: Python :: 3.12
Classifier: Programming Language :: Python :: 3.13
Classifier: Programming Language :: Python :: 3.14
Classifier: Programming Language :: Rust
Classifier: Topic :: Scientific/Engineering :: Mathematics
Classifier: Topic :: Scientific/Engineering :: Physics
Classifier: Typing :: Typed
Requires-Dist: numpy>=2.3.0
License-File: LICENSE-APACHE
License-File: LICENSE-MIT
Summary: A library for random number/stochastic process simulation with high performance.
Keywords: stochastic-processes,simulation,random,scientific-computing
Author-email: tangxiangong <tangxiangong@gmail.com>
License: MIT
Requires-Python: >=3.11
Project-URL: Repository, https://github.com/tangxiangong/py-diffusionx
